MANIFEST.in
README.rst
setup.cfg
setup.py
main/__init__.py
main/__main__.py
ml_py/__init__.py
ml_py.egg-info/PKG-INFO
ml_py.egg-info/SOURCES.txt
ml_py.egg-info/dependency_links.txt
ml_py.egg-info/requires.txt
ml_py.egg-info/top_level.txt
ml_py/image/__init__.py