Metadata-Version: 1.2
Name: ml-py
Version: 0.0.3
Summary: Python packge which contains method used in machine learning projects.
Home-page: https://github.com/mitiku1/ML_PY
Author: Mitiku Yohannes
Author-email: se.mitiku.yohannes@gmail.com
License: UNKNOWN
Project-URL: Source, https://github.com/mitiku1/ML_PY/
Project-URL: Bug Reports, https://github.com/mitiku1/ML_PY/issues
Project-URL: Say Thanks!, https://saythanks.io/to/mitiku1
Keywords: Machine learning tools
Platform: UNKNOWN
Classifier: Development Status :: 3 - Alpha
Classifier: Topic :: Software Development
Classifier: License :: OSI Approved :: MIT License
Classifier: Programming Language :: Python :: 2
Classifier: Programming Language :: Python :: 2.7
Classifier: Programming Language :: Python :: 3
Classifier: Programming Language :: Python :: 3.4
Classifier: Programming Language :: Python :: 3.5
Classifier: Programming Language :: Python :: 3.6
